transaction_manager/__init__.py
transaction_manager/transaction_manager.py
async_transaction_manager-0.1.2.dist-info/METADATA
async_transaction_manager-0.1.2.dist-info/WHEEL
async_transaction_manager-0.1.2.dist-info/top_level.txt
async_transaction_manager-0.1.2.dist-info/RECORD
