Metadata-Version: 2.4
Name: async-transaction-manager
Version: 0.1.2
Summary: A robust asynchronous transaction management library for Python functions.
Home-page: https://github.com/amirmotlagh/transaction-manager
Author: Amir Alaghmandan
Author-email: amir.alaghmand@gmail.com
Project-URL: Bug Tracker, https://github.com/amirmotlagh/transaction-manager/issues
Classifier: Programming Language :: Python :: 3
Classifier: License :: OSI Approved :: MIT License
Classifier: Operating System :: OS Independent
Classifier: Framework :: AsyncIO
Requires-Python: >=3.8
Dynamic: author
Dynamic: author-email
Dynamic: classifier
Dynamic: description
Dynamic: description-content-type
Dynamic: home-page
Dynamic: project-url
Dynamic: requires-python
Dynamic: summary
